{
  "name": "Norman Chapman",
  "age": 39,
  "address": {
    "street": "Sacog Key",
    "city": "Ablazeb",
    "state": "NJ",
    "zip": "43059"
  },
  "contact": {
    "phone": "(970) 330-3310",
    "servicePhone": "800136218"
  },
  "birthday": "1977-08-03T05:07:57.490Z",
  "ip": "164.211.8.181",
  "foo": "bar",
  "profile": {
    "about": "Onni puj tifoos hut ga zal esugogcu hahlu kaz rijal si ov vo ludeliz. Pi pav aducad mol nepiptud zeimamul ela ofaok uji nevhizim mownashec ros inora. Se uz hedo eba ahejial je usoufebek lilom if lirfaw nurimu moghuj cefkadcem keto lozcamin. Wade hu ce mohpow nopwepuf karge uhugawo pa koc ramug foipibuf rir hajwug jasikalu zejeihe ejmi.",
    "bio": "Risubgi ibza od fa pe izna siscavho pid ebu relanted hokpa id zuwfa. Ucegowago diciv ton fi nel fumitib fegpun gic uke luhlud kisalli olpe citjihpe buorkog bepdaleg watawib zuhka. Heb basa pewrapafe opufehhab baz kefheg fabaup na uwvuumo fujho luha ciak husuk sudmajfe burnaac ucakoh wopvetmuc egdagmo. Nizwe tisaezo honji vi gaedeica kaecivem upuum nirgakop upecus en olbisve eculanka bokovne zec ikmu ufsemut. Kiku tagremo ukuiva moeka firlog ruz caushud kupnirvip fimeg hu nasendo ane puh vutgeldil ifavut. Wowimu vogisike kikhiin satuk ko rofhilki asa zof ke susakeje hap asimudwu ha enu juc zem."
  },
  "apiKey": "13a94136c6e3590ac9ff0cabf3d8096006e14fa520cb85b8180211d7488c2c07",
  "currency": {
    "code": "ARS",
    "name": "Argentina Peso"
  }
}