{
  "name": "Randy Ramos",
  "age": 30,
  "address": {
    "street": "Wetup Pass",
    "city": "Bafobe",
    "state": "HI",
    "zip": "90832"
  },
  "contact": {
    "phone": "(319) 760-1078",
    "servicePhone": "800232311"
  },
  "birthday": "1975-07-13T10:00:40.894Z",
  "ip": "52.169.177.50",
  "foo": "bar",
  "profile": {
    "about": "Ocu ar wu rigjamve ice me jadrocu rod eca tosoppej loibda kehmez. Puwa jarhatwid vikgub nuge kawri jewvij uju upgu jocehil webi nullavhu lefosma jodafgoc. Lawso age jus sankindas sapih igwar tecja li wu afzo sag ehu nu louba puviglid. Ruproku kihfuv ozaiw nucagigoz uf ropta leciheg coz vev budcav ipdos onerit. Vehoh icucesa ujgatu vencuc zub pifnu zohbos deza bode ce cum zujwepe geruro ficzawiw paz jovu.",
    "bio": "Su row gup fasazim pom ef kuhus wuf zi ce nibsu ekefonan vom avzurfi. Edope mevumi pev solupru zoca mizib bu mirobcav kuwjem lu powpoj utukil vuv se. Ha it rogse jul vono ep vot vazizoz upiowuof giodu tihzeb fowek hi wopded luvbus ral vogzivtut. Lo vijdodpa leageri ugianu kime fackegeg si ebjerok huvubeb zas weggev rame ba ziguwumof. Duti wo heagva gerfi vitme divepri gopegop col fomoc awma nes ife izfacuh."
  },
  "apiKey": "0bf4d445294ca860471250043ee3cde203357e2a0b9baad8b62f6ef5add99098",
  "currency": {
    "code": "HUF",
    "name": "Hungary Forint"
  }
}